athigeo/__init__.py
athigeo/athigeo.py
athigeo/common.py
athigeo/foliumap.py
athigeo/utils.py
athigeo-0.0.6.dist-info/LICENSE
athigeo-0.0.6.dist-info/METADATA
athigeo-0.0.6.dist-info/WHEEL
athigeo-0.0.6.dist-info/entry_points.txt
athigeo-0.0.6.dist-info/top_level.txt
athigeo-0.0.6.dist-info/RECORD
